<annotation>
	<folder>ayam betutu</folder>
	<filename>ayambetutu11.jpeg</filename>
	<path>D:\capstone\task\Google-Image-Scraper-master\scraping bangkit\ayam betutu\ayambetutu11.jpeg</path>
	<source>
		<database>Unknown</database>
	</source>
	<size>
		<width>958</width>
		<height>714</height>
		<depth>3</depth>
	</size>
	<segmented>0</segmented>
	<object>
		<name>ayam_betutu</name>
		<pose>Unspecified</pose>
		<truncated>0</truncated>
		<difficult>0</difficult>
		<bndbox>
			<xmin>241</xmin>
			<ymin>6</ymin>
			<xmax>837</xmax>
			<ymax>400</ymax>
		</bndbox>
	</object>
</annotation>
