<annotation>
	<folder>rujak cingur</folder>
	<filename>rujakcingur88.jpeg</filename>
	<path>D:\capstone\task\Google-Image-Scraper-master\scraping bangkit\rujak cingur\rujakcingur88.jpeg</path>
	<source>
		<database>Unknown</database>
	</source>
	<size>
		<width>1200</width>
		<height>766</height>
		<depth>3</depth>
	</size>
	<segmented>0</segmented>
	<object>
		<name>rujak_cingur</name>
		<pose>Unspecified</pose>
		<truncated>0</truncated>
		<difficult>0</difficult>
		<bndbox>
			<xmin>114</xmin>
			<ymin>2</ymin>
			<xmax>1118</xmax>
			<ymax>761</ymax>
		</bndbox>
	</object>
</annotation>
